gasflux/__init__.py
gasflux/background.py
gasflux/cli.py
gasflux/gas.py
gasflux/gasflux_config.yaml
gasflux/generate_test_data.py
gasflux/interpolation.py
gasflux/ml.py
gasflux/plotting.py
gasflux/pre_processing.py
gasflux/processing.py
gasflux/processing_pipelines.py
gasflux/reporting.py
gasflux/resources/model.pkl
gasflux/templates/mass_balance_template.html
gasflux/testdata/exampledata.csv
gasflux/testdata/testconfig.yaml
gasflux/testdata/testdata.csv
gasflux-0.2.2.dist-info/licenses/LICENSE
gasflux-0.2.2.dist-info/METADATA
gasflux-0.2.2.dist-info/WHEEL
gasflux-0.2.2.dist-info/entry_points.txt
gasflux-0.2.2.dist-info/top_level.txt
gasflux-0.2.2.dist-info/RECORD
