Metadata-Version: 2.4
Name: gasflux
Version: 0.2.2
Summary: A package to calculate gas emissions fluxes from natural and anthropogenic sources
Author-email: Jamie McQuilkin <jamie.mcquilkin@gmail.com>
License: AGPL-3.0
Project-URL: Homepage, https://gasflux.github.io
Project-URL: Bug Tracker, https://github.com/gasflux/gasflux/issues
Requires-Python: >=3.10
License-File: LICENSE
Requires-Dist: colorama==0.4.6
Requires-Dist: geopandas==0.14.3
Requires-Dist: geopy==2.4.1
Requires-Dist: Jinja2==3.1.6
Requires-Dist: joblib==1.3.2
Requires-Dist: matplotlib==3.10.0
Requires-Dist: molmass==2023.8.30
Requires-Dist: noise==1.2.2
Requires-Dist: numpy==2.1.3
Requires-Dist: pandas==2.2.3
Requires-Dist: plotly==5.20.0
Requires-Dist: pybaselines==1.1.0
Requires-Dist: pytest==8.1.1
Requires-Dist: PyYAML==6.0.1
Requires-Dist: scikit-gstat==1.0.19
Requires-Dist: scikit-image==0.24.0
Requires-Dist: scipy==1.15.1
Requires-Dist: simplekml==1.3.6
Provides-Extra: dev
Requires-Dist: build; extra == "dev"
Requires-Dist: ipykernel; extra == "dev"
Requires-Dist: mypy; extra == "dev"
Requires-Dist: pigar; extra == "dev"
Requires-Dist: pip>23.3; extra == "dev"
Requires-Dist: pre-commit; extra == "dev"
Requires-Dist: pytest; extra == "dev"
Requires-Dist: pytest-mock; extra == "dev"
Requires-Dist: python-semantic-release; extra == "dev"
Requires-Dist: ruff; extra == "dev"
Requires-Dist: safety; extra == "dev"
Requires-Dist: setuptools; extra == "dev"
Requires-Dist: twine; extra == "dev"
Requires-Dist: vulture; extra == "dev"
Dynamic: license-file
